sprig_aes/__init__.py
sprig_aes/cli.py
sprig_aes/core.py
sprig_aes/version.py
sprig_aes-0.6.0.dist-info/LICENSE
sprig_aes-0.6.0.dist-info/METADATA
sprig_aes-0.6.0.dist-info/WHEEL
sprig_aes-0.6.0.dist-info/entry_points.txt
sprig_aes-0.6.0.dist-info/top_level.txt
sprig_aes-0.6.0.dist-info/RECORD
