Metadata-Version: 2.1
Name: sprig-aes
Version: 0.6.0
Author: Isman Firmansyah
Author-email: isman.firmansyah@gmail.com
License:                                  Apache License
Project-URL: Homepage, https://github.com/iromli/sprig-aes
Classifier: Intended Audience :: Developers
Classifier: License :: OSI Approved :: Apache Software License
Classifier: Topic :: Software Development :: Libraries :: Python Modules
Classifier: Programming Language :: Python
Classifier: Programming Language :: Python :: 3.9
Classifier: Programming Language :: Python :: 3.10
Classifier: Programming Language :: Python :: 3.11
Requires-Python: >=3.9
License-File: LICENSE
Requires-Dist: cryptography
Requires-Dist: click
